psychopy_face_api/__init__.py
psychopy_face_api/components/__init__.py
psychopy_face_api/components/faceAPI/__init__.py
psychopy_face_api/components/faceAPI/classic/faceapi.png
psychopy_face_api/components/faceAPI/classic/faceapi@2x.png
psychopy_face_api/components/faceAPI/dark/faceapi.png
psychopy_face_api/components/faceAPI/dark/faceapi@2x.png
psychopy_face_api/components/faceAPI/light/faceapi.png
psychopy_face_api/components/faceAPI/light/faceapi@2x.png
psychopy_face_api-0.0.1.dist-info/METADATA
psychopy_face_api-0.0.1.dist-info/WHEEL
psychopy_face_api-0.0.1.dist-info/entry_points.txt
psychopy_face_api-0.0.1.dist-info/top_level.txt
psychopy_face_api-0.0.1.dist-info/RECORD
