Metadata-Version: 2.2
Name: psychopy-face-api
Version: 0.0.1
Summary: Add support for Face API in PsychoPy experiments
Author-email: OST Science Team <science@opensceincetools.org>
License: MIT
Project-URL: homepage, https://github.com/psychopy/psychopy-face-api
Project-URL: changelog, https://github.com/psychopy/psychopy-face-api/blob/main/CHANGELOG.md
Provides-Extra: docs
Requires-Dist: psychopy; extra == "docs"
Requires-Dist: sphinx; extra == "docs"
Requires-Dist: furo; extra == "docs"
Provides-Extra: tests
Requires-Dist: psychopy; extra == "tests"
Requires-Dist: pytest; extra == "tests"
